app/__init__.py
app/app.py
app/db.py
app/definitions.py
app/static/admin.js
app/static/file.mp3
app/static/icon.png
app/static/join.mp3
app/static/leave.mp3
app/static/msg.mp3
app/static/room.js
app/static/send.mp3
app/static/style.css
app/static/tile.gif
app/static/tile.jpg
app/static/welcome.mp3
app/templates/index.jinja
app/templates/room.jinja
yacscript-0.3.2.dist-info/licenses/COPYING
yacscript-0.3.2.dist-info/WHEEL
yacscript-0.3.2.dist-info/entry_points.txt
yacscript-0.3.2.dist-info/METADATA
yacscript-0.3.2.dist-info/RECORD
