Metadata-Version: 2.4
Name: yacscript
Version: 0.3.2
Summary: yet another chatroom script.
Author: Valine0x
Author-email: Valine0x <me@valine0x.icu>
License-File: COPYING
Requires-Dist: bbcode>=1.1.0
Requires-Dist: captcha>=0.7.1
Requires-Dist: click>=8.2.1
Requires-Dist: flask>=3.1.1
Requires-Dist: flask-socketio>=5.5.1
Requires-Dist: gevent>=25.5.1
Requires-Dist: webargs>=8.7.0
Requires-Python: >=3.13
